nightMARE/__init__.py
nightMARE/analysis/__init__.py
nightMARE/analysis/emulation.py
nightMARE/analysis/reversing.py
nightMARE/core/__init__.py
nightMARE/core/bits.py
nightMARE/core/cast.py
nightMARE/core/regex.py
nightMARE/core/utils.py
nightMARE/core/compression/__init__.py
nightMARE/core/compression/lznt1.py
nightMARE/malware/__init__.py
nightMARE/malware/blister/__init__.py
nightMARE/malware/blister/configuration.py
nightMARE/malware/blister/crypto.py
nightMARE/malware/deprecated/__init__.py
nightMARE/malware/deprecated/icedid/__init__.py
nightMARE/malware/deprecated/icedid/common.py
nightMARE/malware/deprecated/icedid/compression.py
nightMARE/malware/deprecated/icedid/configuration.py
nightMARE/malware/deprecated/icedid/core.py
nightMARE/malware/deprecated/icedid/crypto.py
nightMARE/malware/deprecated/icedid/custom_pe.py
nightMARE/malware/deprecated/icedid/fake_gzip.py
nightMARE/malware/deprecated/icedid/windows.py
nightMARE/malware/ghostpulse/__init__.py
nightMARE/malware/ghostpulse/payload_common.py
nightMARE/malware/ghostpulse/payload_idat.py
nightMARE/malware/ghostpulse/payload_pixels.py
nightMARE/malware/latrodectus/__init__.py
nightMARE/malware/latrodectus/old/__init__.py
nightMARE/malware/latrodectus/old/crypto.py
nightMARE/malware/latrodectus/v1_9/__init__.py
nightMARE/malware/latrodectus/v1_9/configuration.py
nightMARE/malware/latrodectus/v1_9/crypto.py
nightMARE/malware/lobshot/__init__.py
nightMARE/malware/lobshot/configuration.py
nightMARE/malware/lobshot/crypto.py
nightMARE/malware/lumma/__init__.py
nightMARE/malware/lumma/configuration.py
nightMARE/malware/netwire/__init__.py
nightMARE/malware/netwire/configuration.py
nightMARE/malware/redlinestealer/__init__.py
nightMARE/malware/redlinestealer/configuration.py
nightMARE/malware/remcos/__init__.py
nightMARE/malware/remcos/c2.py
nightMARE/malware/remcos/configuration.py
nightMARE/malware/remcos/struct.py
nightMARE/malware/smokeloader/__init__.py
nightMARE/malware/smokeloader/configuration.py
nightmare_lib-0.16.0.dist-info/METADATA
nightmare_lib-0.16.0.dist-info/WHEEL
nightmare_lib-0.16.0.dist-info/top_level.txt
nightmare_lib-0.16.0.dist-info/RECORD
