Metadata-Version: 2.4
Name: nightMARE-lib
Version: 0.16.0
Requires-Python: >=3.10
Requires-Dist: construct==2.10.70
Requires-Dist: dotnetfile==0.2.4
Requires-Dist: fnvhash==0.2.1
Requires-Dist: lief==0.16.4
Requires-Dist: pillow==11.0.0
Requires-Dist: pycryptodome==3.21.0
Requires-Dist: pytest==8.3.5
Requires-Dist: requests==2.32.3
Requires-Dist: rzpipe==0.6.2
Requires-Dist: setuptools==80.9.0
Requires-Dist: unicorn==2.0.1
